sloprank/__init__.py
sloprank/__main__.py
sloprank/cli.py
sloprank/collect.py
sloprank/config.py
sloprank/pandas_backend.py
sloprank/parse.py
sloprank/rank.py
sloprank/utils/__init__.py
sloprank/utils/categorization.py
sloprank/utils/commands.py
sloprank/utils/confidence.py
sloprank/utils/dashboard.py
sloprank/utils/visualization.py
sloprank-0.3.17.dist-info/METADATA
sloprank-0.3.17.dist-info/WHEEL
sloprank-0.3.17.dist-info/entry_points.txt
sloprank-0.3.17.dist-info/top_level.txt
sloprank-0.3.17.dist-info/RECORD
