Metadata-Version: 2.4
Name: sloprank
Version: 0.3.17
Summary: Peer-based LLM cross-evaluation system
Author-email: Rohit Krishnan <rohit.krishnan@gmail.com>
License: Apache License
Project-URL: Homepage, https://github.com/strangeloopcanon/LLMRank
Requires-Python: >=3.9
Requires-Dist: bodo>=2024.0.0
Requires-Dist: openpyxl>=3.0.10
Requires-Dist: networkx>=2.8
Requires-Dist: python-dotenv>=0.21.0
Requires-Dist: click>=8.0.0
Requires-Dist: numpy>=1.20.0
Requires-Dist: matplotlib>=3.5.0
Requires-Dist: llm>=0.13.0
Provides-Extra: pandas
Requires-Dist: pandas>=1.5.0; extra == "pandas"
Provides-Extra: vis
Requires-Dist: plotly>=5.5.0; extra == "vis"
Requires-Dist: kaleido>=0.2.1; extra == "vis"
Provides-Extra: dashboard
Requires-Dist: dash>=2.0.0; extra == "dashboard"
Requires-Dist: dash-bootstrap-components>=1.0.0; extra == "dashboard"
Provides-Extra: full
Requires-Dist: plotly>=5.5.0; extra == "full"
Requires-Dist: kaleido>=0.2.1; extra == "full"
Requires-Dist: dash>=2.0.0; extra == "full"
Requires-Dist: dash-bootstrap-components>=1.0.0; extra == "full"
Requires-Dist: parallm>=0.1.3; extra == "full"
